claude_cache/__init__.py
claude_cache/agent.py
claude_cache/animations.py
claude_cache/auto_config.py
claude_cache/batch_processor.py
claude_cache/behavioral_detector.py
claude_cache/claude_code_mcp.py
claude_cache/cli.py
claude_cache/config.py
claude_cache/context_injector.py
claude_cache/conversation_analyzer.py
claude_cache/cross_project_intelligence.py
claude_cache/daemon.py
claude_cache/differential_learner.py
claude_cache/doc_scanner.py
claude_cache/dual_path_detector.py
claude_cache/enhanced_detector.py
claude_cache/error_pattern_learner.py
claude_cache/execution_monitor.py
claude_cache/extraction_prompts.py
claude_cache/intelligent_detector.py
claude_cache/intent_detector.py
claude_cache/knowledge_base.py
claude_cache/lesson_organizer.py
claude_cache/log_processor.py
claude_cache/log_state.py
claude_cache/log_watcher.py
claude_cache/meta_pattern_scorer.py
claude_cache/pattern_factory.py
claude_cache/realtime_updater.py
claude_cache/semantic_matcher.py
claude_cache/success_detector.py
claude_cache/vector_search.py
claude_cache-0.9.2.dist-info/licenses/LICENSE
claude_cache-0.9.2.dist-info/METADATA
claude_cache-0.9.2.dist-info/WHEEL
claude_cache-0.9.2.dist-info/entry_points.txt
claude_cache-0.9.2.dist-info/top_level.txt
claude_cache-0.9.2.dist-info/RECORD
