Metadata-Version: 2.4
Name: claude-cache
Version: 0.9.2
Summary: Perfect memory for Claude - Never solve the same coding problem twice
Author-email: Ga1ien <g@braintied.com>
Maintainer-email: Ga1ien <g@braintied.com>
License: MIT
Project-URL: Homepage, https://github.com/ga1ien/claude-cache
Project-URL: Bug Tracker, https://github.com/ga1ien/claude-cache/issues
Project-URL: Source, https://github.com/ga1ien/claude-cache
Keywords: claude,ai,cache,memory,coding-assistant,claude-code,cursor
Classifier: Development Status :: 4 - Beta
Classifier: Intended Audience :: Developers
Classifier: Topic :: Software Development :: Libraries :: Python Modules
Classifier: License :: OSI Approved :: MIT License
Classifier: Programming Language :: Python :: 3
Classifier: Programming Language :: Python :: 3.8
Classifier: Programming Language :: Python :: 3.9
Classifier: Programming Language :: Python :: 3.10
Classifier: Programming Language :: Python :: 3.11
Classifier: Operating System :: OS Independent
Requires-Python: >=3.8
License-File: LICENSE
Requires-Dist: watchdog>=3.0.0
Requires-Dist: click>=8.0.0
Requires-Dist: rich>=13.0.0
Requires-Dist: scikit-learn>=1.3.0
Requires-Dist: numpy>=1.24.0
Requires-Dist: python-dotenv>=1.0.0
Provides-Extra: dev
Requires-Dist: pytest>=7.0.0; extra == "dev"
Requires-Dist: black>=23.0.0; extra == "dev"
Requires-Dist: isort>=5.0.0; extra == "dev"
Requires-Dist: mypy>=1.0.0; extra == "dev"
Provides-Extra: enhanced
Requires-Dist: sentence-transformers>=2.2.0; extra == "enhanced"
Provides-Extra: mcp
Requires-Dist: mcp>=1.14.0; extra == "mcp"
Provides-Extra: all
Requires-Dist: sentence-transformers>=2.2.0; extra == "all"
Requires-Dist: mcp>=1.14.0; extra == "all"
Dynamic: license-file
